glouton/__init__.py
glouton/commands/__init__.py
glouton/commands/download/__init__.py
glouton/commands/download/archiveDownloadCommand.py
glouton/commands/download/demoddataDownloadCommand.py
glouton/commands/download/downloadCommand.py
glouton/commands/download/downloadCommandParams.py
glouton/commands/download/downloadObservationCommand.py
glouton/commands/download/downloadTelemetryCommand.py
glouton/commands/download/frameDownloadCommand.py
glouton/commands/download/waterfallDownloadCommand.py
glouton/commands/module/__init__.py
glouton/commands/module/endModuleCommand.py
glouton/commands/module/endModuleCommandParams.py
glouton/commands/module/moduleCommand.py
glouton/commands/module/moduleCommandParams.py
glouton/commands/module/observationModuleCommand.py
glouton/commands/module/observationModuleCommandParams.py
glouton/commands/module/telemetryModuleCommand.py
glouton/commands/module/telemetryModuleCommandParams.py
glouton/domain/__init__.py
glouton/domain/interfaces/__init__.py
glouton/domain/interfaces/downloadable.py
glouton/domain/parameters/__init__.py
glouton/domain/parameters/programCmd.py
glouton/infrastructure/__init__.py
glouton/infrastructure/satnogClient.py
glouton/infrastructure/satnogDbClient.py
glouton/infrastructure/satnogNetworkClient.py
glouton/modules/__init__.py
glouton/modules/csv.py
glouton/modules/flagnoimagenexusframe.py
glouton/modules/moduleBase.py
glouton/modules/ntpainaniimagedecoder.py
glouton/modules/observationModuleBase.py
glouton/modules/obsmetadatatojsonfile.py
glouton/modules/painaniDecoder.py
glouton/modules/painaniimagedecoder.py
glouton/modules/polaris.py
glouton/modules/telemetryModuleBase.py
glouton/modules/testmodule.py
glouton/repositories/__init__.py
glouton/repositories/archive/__init__.py
glouton/repositories/archive/archiveRepo.py
glouton/repositories/demoddata/__init__.py
glouton/repositories/demoddata/demoddataRepo.py
glouton/repositories/frame/__init__.py
glouton/repositories/frame/frameRepo.py
glouton-0.12.0.dist-info/LICENSE
glouton-0.12.0.dist-info/METADATA
glouton-0.12.0.dist-info/WHEEL
glouton-0.12.0.dist-info/top_level.txt
glouton-0.12.0.dist-info/RECORD
