Metadata-Version: 2.1
Name: glouton
Version: 0.12.0
Summary: `Glouton is a cli program which helps you downloading satnogs data`
Home-page: https://github.com/deckbsd/glouton-satnogs-data-downloader.git
Author: deckbsd
License: MIT
Keywords: satnogs,telemetry,satellite,archive,data,db,download
Platform: UNKNOWN
Classifier: Development Status :: 3 - Alpha
Classifier: Intended Audience :: Developers
Classifier: Programming Language :: Python :: 3
Classifier: License :: OSI Approved :: MIT License
Requires-Python: >=3
Requires-Dist: requests
Provides-Extra: test
Requires-Dist: pytest ; extra == 'test'
